overinstall/__init__.py
overinstall/installer.py
overinstall-0.1.0.dist-info/METADATA
overinstall-0.1.0.dist-info/WHEEL
overinstall-0.1.0.dist-info/top_level.txt
overinstall-0.1.0.dist-info/RECORD
