Metadata-Version: 2.4
Name: overinstall
Version: 0.1.0
Summary: Auto-installs all Python dependencies for your project
Author: xxDawid
Author-email: xxDawid <xxdawid.xyz@gmail.com>
Requires-Python: >=3.7
Dynamic: author
Dynamic: requires-python
